{
  "app": {
    "[project]/app/_not-found/page": [
      "static/media/83afe278b6a6bb3c-s.p.0q-301v4kxxnr.woff2"
    ],
    "[project]/app/about/page": [
      "static/media/83afe278b6a6bb3c-s.p.0q-301v4kxxnr.woff2"
    ],
    "[project]/app/contact/page": [
      "static/media/83afe278b6a6bb3c-s.p.0q-301v4kxxnr.woff2"
    ],
    "[project]/app/insights/[slug]/page": [
      "static/media/83afe278b6a6bb3c-s.p.0q-301v4kxxnr.woff2"
    ],
    "[project]/app/insights/page": [
      "static/media/83afe278b6a6bb3c-s.p.0q-301v4kxxnr.woff2"
    ],
    "[project]/app/japan-apostille/page": [
      "static/media/83afe278b6a6bb3c-s.p.0q-301v4kxxnr.woff2"
    ],
    "[project]/app/korea-apostille/page": [
      "static/media/83afe278b6a6bb3c-s.p.0q-301v4kxxnr.woff2"
    ],
    "[project]/app/page": [
      "static/media/83afe278b6a6bb3c-s.p.0q-301v4kxxnr.woff2"
    ],
    "[project]/app/services/[slug]/page": [
      "static/media/83afe278b6a6bb3c-s.p.0q-301v4kxxnr.woff2"
    ],
    "[project]/app/services/page": [
      "static/media/83afe278b6a6bb3c-s.p.0q-301v4kxxnr.woff2"
    ],
    "[project]/app/shanghai-fingerprinting/page": [
      "static/media/83afe278b6a6bb3c-s.p.0q-301v4kxxnr.woff2"
    ],
    "[project]/app/thailand-authentication/page": [
      "static/media/83afe278b6a6bb3c-s.p.0q-301v4kxxnr.woff2"
    ],
    "[project]/app/vietnam-authentication/page": [
      "static/media/83afe278b6a6bb3c-s.p.0q-301v4kxxnr.woff2"
    ],
    "[project]/app/zh/about/page": [
      "static/media/83afe278b6a6bb3c-s.p.0q-301v4kxxnr.woff2"
    ],
    "[project]/app/zh/contact/page": [
      "static/media/83afe278b6a6bb3c-s.p.0q-301v4kxxnr.woff2"
    ],
    "[project]/app/zh/insights/[slug]/page": [
      "static/media/83afe278b6a6bb3c-s.p.0q-301v4kxxnr.woff2"
    ],
    "[project]/app/zh/insights/page": [
      "static/media/83afe278b6a6bb3c-s.p.0q-301v4kxxnr.woff2"
    ],
    "[project]/app/zh/page": [
      "static/media/83afe278b6a6bb3c-s.p.0q-301v4kxxnr.woff2"
    ],
    "[project]/app/zh/services/page": [
      "static/media/83afe278b6a6bb3c-s.p.0q-301v4kxxnr.woff2"
    ],
    "[project]/app/zh/shanghai-fingerprinting/page": [
      "static/media/83afe278b6a6bb3c-s.p.0q-301v4kxxnr.woff2"
    ]
  },
  "appUsingSizeAdjust": true,
  "pages": {},
  "pagesUsingSizeAdjust": false
}